d2l/__init__.py
d2l/jax.py
d2l/mxnet.py
d2l/tensorflow.py
d2l/torch.py
d2l-1.0.3.dist-info/LICENSE
d2l-1.0.3.dist-info/LICENSE-SAMPLECODE
d2l-1.0.3.dist-info/LICENSE-SUMMARY
d2l-1.0.3.dist-info/METADATA
d2l-1.0.3.dist-info/WHEEL
d2l-1.0.3.dist-info/top_level.txt
d2l-1.0.3.dist-info/zip-safe
d2l-1.0.3.dist-info/RECORD
